pas_tui/__init__.py
pas_tui/core.py
pas_tui-2026.1.20.2.dist-info/METADATA
pas_tui-2026.1.20.2.dist-info/WHEEL
pas_tui-2026.1.20.2.dist-info/RECORD
