Metadata-Version: 2.4
Name: pas-tui
Version: 2026.1.20.2
Summary: A professional, hotkey-driven TUI system for Python CLIs
Project-URL: Homepage, https://github.com/nextoken/pas
Author-email: Next Token <nextoken@gmail.com>
License: MIT
Requires-Python: >=3.8
Requires-Dist: prompt-toolkit>=3.0.0
Requires-Dist: questionary>=2.0.0
Requires-Dist: rich>=13.0.0
